upic/__init__.py
upic/modules/logger.py
upic/vision/tagdetector.py
upicvision-0.1.1.dist-info/METADATA
upicvision-0.1.1.dist-info/WHEEL
upicvision-0.1.1.dist-info/entry_points.txt
upicvision-0.1.1.dist-info/licenses/LICENSE
upicvision-0.1.1.dist-info/RECORD
