Metadata-Version: 2.1
Name: upicvision
Version: 0.1.1
Summary: pi vision lib
Author-Email: Whth <88489697+Whth@users.noreply.github.com>
License: MIT License
Classifier: License :: OSI Approved :: MIT License
Classifier: Programming Language :: Python :: 3.11
Classifier: Programming Language :: Python :: Implementation :: CPython
Classifier: Framework :: Pydantic :: 2
Requires-Python: >=3.11
Requires-Dist: coloredlogs>=15.0.1
Requires-Dist: numpy>=2.0.0
Requires-Dist: opencv-python-headless>=4.10.0.84
Requires-Dist: pyapriltags>=3.3.0.3
